cloudmask/__init__.py
cloudmask/__version__.py
cloudmask/anonymizer.py
cloudmask/core.py
cloudmask/exceptions.py
cloudmask/logging.py
cloudmask/mapper.py
cloudmask/py.typed
cloudmask/cli/__init__.py
cloudmask/cli/__main__.py
cloudmask/cli/cli.py
cloudmask/cli/cli_handlers.py
cloudmask/config/__init__.py
cloudmask/config/config.py
cloudmask/config/config_loader.py
cloudmask/config/config_templates.py
cloudmask/io/__init__.py
cloudmask/io/file_processor.py
cloudmask/io/storage.py
cloudmask/io/streaming.py
cloudmask/utils/__init__.py
cloudmask/utils/cache.py
cloudmask/utils/patterns.py
cloudmask/utils/ratelimit.py
cloudmask/utils/security.py
cloudmask_aws-0.4.1.dist-info/licenses/LICENSE
cloudmask_aws-0.4.1.dist-info/METADATA
cloudmask_aws-0.4.1.dist-info/WHEEL
cloudmask_aws-0.4.1.dist-info/entry_points.txt
cloudmask_aws-0.4.1.dist-info/top_level.txt
cloudmask_aws-0.4.1.dist-info/RECORD
