Metadata-Version: 2.4
Name: cloudmask-aws
Version: 0.4.1
Summary: Anonymize AWS infrastructure identifiers for secure LLM processing
Author-email: Sam Fakhreddine <sam.fakhreddine@gmail.com>
Maintainer-email: Sam Fakhreddine <sam.fakhreddine@gmail.com>
License: MIT
Project-URL: Homepage, https://github.com/sam-fakhreddine/cloudmask-aws
Project-URL: Documentation, https://github.com/sam-fakhreddine/cloudmask-aws#readme
Project-URL: Repository, https://github.com/sam-fakhreddine/cloudmask-aws
Project-URL: Bug Tracker, https://github.com/sam-fakhreddine/cloudmask-aws/issues
Project-URL: Changelog, https://github.com/sam-fakhreddine/cloudmask-aws/blob/main/CHANGELOG.md
Project-URL: Source Code, https://github.com/sam-fakhreddine/cloudmask-aws
Keywords: aws,anonymization,security,privacy,llm,infrastructure,cloud,data-privacy,pii,masking,obfuscation
Classifier: Development Status :: 4 - Beta
Classifier: Intended Audience :: Developers
Classifier: Intended Audience :: System Administrators
Classifier: License :: OSI Approved :: MIT License
Classifier: Operating System :: OS Independent
Classifier: Programming Language :: Python :: 3
Classifier: Programming Language :: Python :: 3.10
Classifier: Programming Language :: Python :: 3.11
Classifier: Programming Language :: Python :: 3.12
Classifier: Programming Language :: Python :: 3.13
Classifier: Programming Language :: Python :: 3 :: Only
Classifier: Topic :: Security
Classifier: Topic :: Software Development :: Libraries :: Python Modules
Classifier: Topic :: System :: Systems Administration
Classifier: Topic :: Utilities
Classifier: Typing :: Typed
Requires-Python: >=3.10
License-File: LICENSE
Requires-Dist: pyyaml>=6.0.3
Requires-Dist: pyperclip>=1.11.0
Requires-Dist: cryptography>=41.0.0
Provides-Extra: dev
Requires-Dist: pytest>=8.4.2; extra == "dev"
Requires-Dist: pytest-cov>=7.0.0; extra == "dev"
Requires-Dist: black>=25.9.0; extra == "dev"
Requires-Dist: ruff>=0.14.0; extra == "dev"
Requires-Dist: mypy>=1.18.2; extra == "dev"
Requires-Dist: types-tqdm>=4.66.0; extra == "dev"
Requires-Dist: pydocstyle>=6.3.0; extra == "dev"
Requires-Dist: pre-commit>=4.3.0; extra == "dev"
Requires-Dist: sphinx>=7.0.0; extra == "dev"
Requires-Dist: sphinx-rtd-theme>=2.0.0; extra == "dev"
Requires-Dist: tqdm>=4.66.0; extra == "dev"
Provides-Extra: performance
Requires-Dist: tqdm>=4.66.0; extra == "performance"
Dynamic: license-file
